monito_tools/__init__.py
monito_tools/bin/monito_analysis.py
monito_tools/bin/monito_similarity.py
monito_tools/bin/monito_similarity_simple.py
monito_tools/bin/monito_stats.py
monito_tools/lib/config.py
monito_tools/lib/db.py
monito_tools/lib/helpers.py
monito_tools/lib/log.py
monito_tools/lib/text.py
monito_tools/lib/topics.py
monito_tools-0.1.0.dist-info/METADATA
monito_tools-0.1.0.dist-info/WHEEL
monito_tools-0.1.0.dist-info/RECORD
